[
  {"day": "poniedziałek", "hour": "7:50", "teacher": ["Szik S."], "place": "Front"},
  {"day": "poniedziałek", "hour": "8:45", "teacher": ["Wrona"], "place": "Front"},
  {"day": "poniedziałek", "hour": "9:40", "teacher": ["Wrotna"], "place": "Front"},
  {"day": "poniedziałek", "hour": "7:50", "teacher": ["Kajetanowicz"], "place": "Dziedziniec"},
  {"day": "poniedziałek", "hour": "8:45", "teacher": ["Kajetanowicz"], "place": "Dziedziniec"},
  {"day": "poniedziałek", "hour": "9:40", "teacher": ["Jop"], "place": "Dziedziniec"},
  {"day": "poniedziałek", "hour": "10:35", "teacher": ["Woźniak"], "place": "Dziedziniec"},
  {"day": "poniedziałek", "hour": "11:30", "teacher": ["Trela"], "place": "Dziedziniec"},
  {"day": "poniedziałek", "hour": "12:25", "teacher": ["Nogawka"], "place": "Dziedziniec"},
  {"day": "poniedziałek", "hour": "13:20", "teacher": ["Wysocka"], "place": "Dziedziniec"},
  {"day": "poniedziałek", "hour": "14:20", "teacher": ["Wysocka"], "place": "Dziedziniec"},
  {"day": "poniedziałek", "hour": "15:10", "teacher": ["Wysocka"], "place": "Dziedziniec"},
  {"day": "poniedziałek", "hour": "7:50", "teacher": ["Sala"], "place": "Budynek A"},
  {"day": "poniedziałek", "hour": "8:45", "teacher": ["Dyła"], "place": "Budynek A"},
  {"day": "poniedziałek", "hour": "9:40", "teacher": ["Dyła"], "place": "Budynek A"},
  {"day": "poniedziałek", "hour": "10:35", "teacher": ["Dyła"], "place": "Budynek A"},
  {"day": "poniedziałek", "hour": "11:30", "teacher": ["Dyła"], "place": "Budynek A"},
  {"day": "poniedziałek", "hour": "12:25", "teacher": ["Witkowski"], "place": "Budynek A"},
  {"day": "poniedziałek", "hour": "13:20", "teacher": ["Szik I."], "place": "Budynek A"},
  {"day": "poniedziałek", "hour": "14:20", "teacher": ["Witkowski"], "place": "Budynek A"},
  {"day": "poniedziałek", "hour": "7:50", "teacher": ["Woźniak"], "place": "Budynek A 1piętro"},
  {"day": "poniedziałek", "hour": "8:45", "teacher": ["Kupczyk"], "place": "Budynek A 1piętro"},
  {"day": "poniedziałek", "hour": "9:40", "teacher": ["Kupczyk"], "place": "Budynek A 1piętro"},
  {"day": "poniedziałek", "hour": "10:35", "teacher": ["Długosz-Pasieka"], "place": "Budynek A 1piętro"},
  {"day": "poniedziałek", "hour": "11:30", "teacher": ["Rzemińska"], "place": "Budynek A 1piętro"},
  {"day": "poniedziałek", "hour": "12:25", "teacher": null, "place": "Budynek A 1piętro"},
  {"day": "poniedziałek", "hour": "13:20", "teacher": null, "place": "Budynek A 1piętro"},
  {"day": "poniedziałek", "hour": "14:20", "teacher": ["Witkowski"], "place": "Budynek A 1piętro"},
  {"day": "poniedziałek", "hour": "7:50", "teacher": ["Szkudlarek", "Wrona"], "place": "Boisko"},
  {"day": "poniedziałek", "hour": "8:45", "teacher": ["Łukaszuk", "Sala"], "place": "Boisko"},
  {"day": "poniedziałek", "hour": "9:40", "teacher": ["Łukaszuk", "Sala"], "place": "Boisko"},
  {"day": "poniedziałek", "hour": "10:35", "teacher": ["Szkudlarek", "Boruk"], "place": "Boisko"},
  {"day": "poniedziałek", "hour": "11:30", "teacher": ["Szkudlarek", "Słomski"], "place": "Boisko"},
  {"day": "poniedziałek", "hour": "12:25", "teacher": ["Łukaszuk", "Słomski"], "place": "Boisko"},
  {"day": "poniedziałek", "hour": "13:20", "teacher": ["Łukaszuk", "Słomski"], "place": "Boisko"},
  {"day": "poniedziałek", "hour": "14:20", "teacher": ["Trela"], "place": "Boisko"},
  {"day": "poniedziałek", "hour": "15:10", "teacher": ["Trela"], "place": "Boisko"},
  {"day": "poniedziałek", "hour": "7:50", "teacher": ["Boruk"], "place": "Budynek B parter + WC"},
  {"day": "poniedziałek", "hour": "8:45", "teacher": ["Boruk"], "place": "Budynek B parter + WC"},
  {"day": "poniedziałek", "hour": "9:40", "teacher": ["Długosz-Pasieka"], "place": "Budynek B parter + WC"},
  {"day": "poniedziałek", "hour": "10:35", "teacher": ["Kajetanowicz"], "place": "Budynek B parter + WC"},
  {"day": "poniedziałek", "hour": "11:30", "teacher": ["Foryt"], "place": "Budynek B parter + WC"},
  {"day": "poniedziałek", "hour": "12:25", "teacher": ["Foryt"], "place": "Budynek B parter + WC"},
  {"day": "poniedziałek", "hour": "13:20", "teacher": ["Woźniak"], "place": "Budynek B parter + WC"},
  {"day": "poniedziałek", "hour": "7:50", "teacher": ["Foryt"], "place": "Budynek B 1piętro"},
  {"day": "poniedziałek", "hour": "8:45", "teacher": ["Nogawka"], "place": "Budynek B 1piętro"},
  {"day": "poniedziałek", "hour": "9:40", "teacher": ["Nogawka"], "place": "Budynek B 1piętro"},
  {"day": "poniedziałek", "hour": "10:35", "teacher": ["Jop"], "place": "Budynek B 1piętro"},
  {"day": "poniedziałek", "hour": "11:30", "teacher": ["Długosz-Pasieka"], "place": "Budynek B 1piętro"},
  {"day": "poniedziałek", "hour": "12:25", "teacher": ["Szkudlarek"], "place": "Budynek B 1piętro"},
  {"day": "poniedziałek", "hour": "13:20", "teacher": ["Trela"], "place": "Budynek B 1piętro"},
  {"day": "wtorek", "hour": "7:50", "teacher": ["Foryt"], "place": "Front"},
  {"day": "wtorek", "hour": "8:45", "teacher": ["Woźniak"], "place": "Front"},
  {"day": "wtorek", "hour": "9:40", "teacher": ["Trela"], "place": "Front"},
  {"day": "wtorek", "hour": "7:50", "teacher": ["Dyła"], "place": "Dziedziniec"},
  {"day": "wtorek", "hour": "8:45", "teacher": ["Dyła"], "place": "Dziedziniec"},
  {"day": "wtorek", "hour": "9:40", "teacher": ["Dyła"], "place": "Dziedziniec"},
  {"day": "wtorek", "hour": "10:35", "teacher": ["Rzemińska"], "place": "Dziedziniec"},
  {"day": "wtorek", "hour": "11:30", "teacher": ["Szik S."], "place": "Dziedziniec"},
  {"day": "wtorek", "hour": "12:25", "teacher": ["Szik S."], "place": "Dziedziniec"},
  {"day": "wtorek", "hour": "13:20", "teacher": ["Szewczak-Świrska"], "place": "Dziedziniec"},
  {"day": "wtorek", "hour": "14:20", "teacher": ["Wrotna"], "place": "Dziedziniec"},
  {"day": "wtorek", "hour": "15:10", "teacher": ["Szewczak-Świrska"], "place": "Dziedziniec"},
  {"day": "wtorek", "hour": "7:50", "teacher": ["Trela"], "place": "Budynek A"},
  {"day": "wtorek", "hour": "8:45", "teacher": ["Wadowski"], "place": "Budynek A"},
  {"day": "wtorek", "hour": "9:40", "teacher": ["Wadowski"], "place": "Budynek A"},
  {"day": "wtorek", "hour": "10:35", "teacher": ["Wadowski"], "place": "Budynek A"},
  {"day": "wtorek", "hour": "11:30", "teacher": ["Wrona"], "place": "Budynek A"},
  {"day": "wtorek", "hour": "12:25", "teacher": ["Słomski"], "place": "Budynek A"},
  {"day": "wtorek", "hour": "13:20", "teacher": ["Woźniak"], "place": "Budynek A"},
  {"day": "wtorek", "hour": "14:20", "teacher": ["Słomski"], "place": "Budynek A"},
  {"day": "wtorek", "hour": "15:10", "teacher": ["Wrotna"], "place": "Budynek A"},
    {"day": "wtorek", "hour": "15:10", "teacher": ["Wrotna"], "place": "Budynek A"},
  {"day": "wtorek", "hour": "7:50", "teacher": null, "place": "Budynek A 1piętro"},
  {"day": "wtorek", "hour": "8:45", "teacher": ["Słomski"], "place": "Budynek A 1piętro"},
  {"day": "wtorek", "hour": "9:40", "teacher": ["Foryt"], "place": "Budynek A 1piętro"},
  {"day": "wtorek", "hour": "10:35", "teacher": null, "place": "Budynek A 1piętro"},
  {"day": "wtorek", "hour": "11:30", "teacher": ["Długosz-Pasieka"], "place": "Budynek A 1piętro"},
  {"day": "wtorek", "hour": "12:25", "teacher": ["Woźniak"], "place": "Budynek A 1piętro"},
  {"day": "wtorek", "hour": "13:20", "teacher": ["Witkowski"], "place": "Budynek A 1piętro"},
  {"day": "wtorek", "hour": "14:20", "teacher": ["Boruk"], "place": "Budynek A 1piętro"},
  {"day": "wtorek", "hour": "15:10", "teacher": ["Woźniak"], "place": "Budynek A 1piętro"},
  {"day": "wtorek", "hour": "7:50", "teacher": ["Szik S.", "Wrona"], "place": "Boisko"},
  {"day": "wtorek", "hour": "8:45", "teacher": ["Rzemińska", "Sala"], "place": "Boisko"},
  {"day": "wtorek", "hour": "9:40", "teacher": ["Rzemińska", "Łukaszuk"], "place": "Boisko"},
  {"day": "wtorek", "hour": "10:35", "teacher": ["Sala", "Słomski"], "place": "Boisko"},
  {"day": "wtorek", "hour": "11:30", "teacher": ["Foryt", "Łukaszuk"], "place": "Boisko"},
  {"day": "wtorek", "hour": "12:25", "teacher": ["Długosz-Pasieka", "Łukaszuk"], "place": "Boisko"},
  {"day": "wtorek", "hour": "13:20", "teacher": ["Szkudlarek", "Boruk"], "place": "Boisko"},
  {"day": "wtorek", "hour": "14:20", "teacher": ["Wrona", "Witkowski"], "place": "Boisko"},
  {"day": "wtorek", "hour": "15:10", "teacher": ["Skórzecka"], "place": "Boisko"},
  {"day": "wtorek", "hour": "7:50", "teacher": ["Kajetanowicz"], "place": "Budynek B parter + WC"},
  {"day": "wtorek", "hour": "8:45", "teacher": ["Jop"], "place": "Budynek B parter + WC"},
  {"day": "wtorek", "hour": "9:40", "teacher": ["Jop"], "place": "Budynek B parter + WC"},
  {"day": "wtorek", "hour": "10:35", "teacher": ["Woźniak"], "place": "Budynek B parter + WC"},
  {"day": "wtorek", "hour": "11:30", "teacher": ["Kajetanowicz"], "place": "Budynek B parter + WC"},
  {"day": "wtorek", "hour": "12:25", "teacher": ["Nogawka"], "place": "Budynek B parter + WC"},
  {"day": "wtorek", "hour": "13:20", "teacher": ["Wadowski"], "place": "Budynek B parter + WC"},
  {"day": "wtorek", "hour": "14:20", "teacher": ["Nogawka"], "place": "Budynek B parter + WC"},
  {"day": "wtorek", "hour": "15:10", "teacher": ["Nogawka"], "place": "Budynek B parter + WC"},
  {"day": "wtorek", "hour": "7:50", "teacher": ["Jop"], "place": "Budynek B 1piętro"},
  {"day": "wtorek", "hour": "8:45", "teacher": ["Kupczyk"], "place": "Budynek B 1piętro"},
  {"day": "wtorek", "hour": "9:40", "teacher": ["Kupczyk"], "place": "Budynek B 1piętro"},
  {"day": "wtorek", "hour": "10:35", "teacher": ["Kupczyk"], "place": "Budynek B 1piętro"},
  {"day": "wtorek", "hour": "11:30", "teacher": ["Nogawka"], "place": "Budynek B 1piętro"},
  {"day": "wtorek", "hour": "12:25", "teacher": ["Szkudlarek"], "place": "Budynek B 1piętro"},
  {"day": "wtorek", "hour": "13:20", "teacher": ["Wrona"], "place": "Budynek B 1piętro"},
  {"day": "wtorek", "hour": "14:20", "teacher": ["Nogawka"], "place": "Budynek B 1piętro"},
  {"day": "wtorek", "hour": "15:10", "teacher": ["Nogawka"], "place": "Budynek B 1piętro"},
  {"day": "środa", "hour": "7:50", "teacher": ["Szkudlarek"], "place": "Front"},
  {"day": "środa", "hour": "8:45", "teacher": ["Słomski"], "place": "Front"},
  {"day": "środa", "hour": "9:40", "teacher": ["Słomski"], "place": "Front"},
  {"day": "środa", "hour": "7:50", "teacher": ["Jop"], "place": "Dziedziniec"},
  {"day": "środa", "hour": "8:45", "teacher": ["Foryt"], "place": "Dziedziniec"},
  {"day": "środa", "hour": "9:40", "teacher": ["Kupczyk"], "place": "Dziedziniec"},
  {"day": "środa", "hour": "10:35", "teacher": ["Kupczyk"], "place": "Dziedziniec"},
  {"day": "środa", "hour": "11:30", "teacher": ["Jop"], "place": "Dziedziniec"},
  {"day": "środa", "hour": "12:25", "teacher": ["Wrotna"], "place": "Dziedziniec"},
  {"day": "środa", "hour": "13:20", "teacher": ["Długosz-Pasieka"], "place": "Dziedziniec"},
  {"day": "środa", "hour": "14:20", "teacher": ["Wrona"], "place": "Dziedziniec"},
  {"day": "środa", "hour": "15:10", "teacher": ["Dębowski"], "place": "Dziedziniec"},
  {"day": "środa", "hour": "7:50", "teacher": ["Dymek"], "place": "Budynek A"},
  {"day": "środa", "hour": "8:45", "teacher": ["Wadowski"], "place": "Budynek A"},
  {"day": "środa", "hour": "9:40", "teacher": ["Wadowski"], "place": "Budynek A"},
  {"day": "środa", "hour": "10:35", "teacher": ["Długosz-Pasieka"], "place": "Budynek A"},
  {"day": "środa", "hour": "11:30", "teacher": ["Dyła"], "place": "Budynek A"},
  {"day": "środa", "hour": "12:25", "teacher": ["Dyła"], "place": "Budynek A"},
  {"day": "środa", "hour": "13:20", "teacher": ["Dyła"], "place": "Budynek A"},
  {"day": "środa", "hour": "14:20", "teacher": ["Wrona"], "place": "Budynek A"},
  {"day": "środa", "hour": "15:10", "teacher": ["Wrotna"], "place": "Budynek A"},
  {"day": "środa", "hour": "7:50", "teacher": ["Wysocka"], "place": "Budynek A 1piętro"},
  {"day": "środa", "hour": "8:45", "teacher": ["Sala"], "place": "Budynek A 1piętro"},
  {"day": "środa", "hour": "9:40", "teacher": null, "place": "Budynek A 1piętro"},
  {"day": "środa", "hour": "10:35", "teacher": null, "place": "Budynek A 1piętro"},
  {"day": "środa", "hour": "11:30", "teacher": ["Kajetanowicz"], "place": "Budynek A 1piętro"},
  {"day": "środa", "hour": "12:25", "teacher": ["Szkudlarek"], "place": "Budynek A 1piętro"},
  {"day": "środa", "hour": "13:20", "teacher": ["Witkowski"], "place": "Budynek A 1piętro"},
  {"day": "środa", "hour": "14:20", "teacher": ["Długosz-Pasieka"], "place": "Budynek A 1piętro"},
  {"day": "środa", "hour": "7:50", "teacher": ["Skórzecka", "Wrona"], "place": "Boisko"},
  {"day": "środa", "hour": "8:45", "teacher": ["Rzemińska", "Woźniak"], "place": "Boisko"},
  {"day": "środa", "hour": "9:40", "teacher": ["Szik S.", "Rzemińska"], "place": "Boisko"},
  {"day": "środa", "hour": "10:35", "teacher": ["Łukaszuk", "Wrona"], "place": "Boisko"},
  {"day": "środa", "hour": "11:30", "teacher": ["Łukaszuk", "Słomski"], "place": "Boisko"},
  {"day": "środa", "hour": "12:25", "teacher": ["Łukaszuk", "Wrona"], "place": "Boisko"},
  {"day": "środa", "hour": "13:20", "teacher": ["Dębowski"], "place": "Boisko"},
  {"day": "środa", "hour": "14:20", "teacher": ["Witkowski"], "place": "Boisko"},
  {"day": "środa", "hour": "15:10", "teacher": ["Witkowski"], "place": "Boisko"},
  {"day": "środa", "hour": "7:50", "teacher": ["Szik I."], "place": "Budynek B parter + WC"},
  {"day": "środa", "hour": "8:45", "teacher": ["Kajetanowicz"], "place": "Budynek B parter + WC"},
  {"day": "środa", "hour": "9:40", "teacher": ["Kajetanowicz"], "place": "Budynek B parter + WC"},
  {"day": "środa", "hour": "10:35", "teacher": ["Szkudlarek"], "place": "Budynek B parter + WC"},
  {"day": "środa", "hour": "11:30", "teacher": ["Foryt"], "place": "Budynek B parter + WC"},
  {"day": "środa", "hour": "7:50", "teacher": ["Nogawka"], "place": "Budynek B 1piętro"},
  {"day": "środa", "hour": "8:45", "teacher": ["Kupczyk"], "place": "Budynek B 1piętro"},
  {"day": "środa", "hour": "9:40", "teacher": ["Foryt"], "place": "Budynek B 1piętro"},
  {"day": "środa", "hour": "10:35", "teacher": ["Foryt"], "place": "Budynek B 1piętro"},
  {"day": "środa", "hour": "11:30", "teacher": ["Szik S."], "place": "Budynek B 1piętro"},
  {"day": "środa", "hour": "12:25", "teacher": ["Szik S."], "place": "Budynek B 1piętro"},
  {"day": "czwartek", "hour": "7:50", "teacher": ["Wrona"], "place": "Front"},
  {"day": "czwartek", "hour": "8:45", "teacher": ["Kupczyk"], "place": "Front"},
  {"day": "czwartek", "hour": "9:40", "teacher": ["Wrona"], "place": "Front"},
  {"day": "czwartek", "hour": "7:50", "teacher": ["Szkudlarek"], "place": "Dziedziniec"},
  {"day": "czwartek", "hour": "8:45", "teacher": ["Nogawka"], "place": "Dziedziniec"},
  {"day": "czwartek", "hour": "9:40", "teacher": ["Kupczyk"], "place": "Dziedziniec"},
  {"day": "czwartek", "hour": "10:35", "teacher": ["Jop"], "place": "Dziedziniec"},
  {"day": "czwartek", "hour": "11:30", "teacher": ["Wrotna"], "place": "Dziedziniec"},
  {"day": "czwartek", "hour": "12:25", "teacher": ["Foryt"], "place": "Dziedziniec"},
  {"day": "czwartek", "hour": "13:20", "teacher": ["Szkudlarek"], "place": "Dziedziniec"},
  {"day": "czwartek", "hour": "14:20", "teacher": ["Rzemińska"], "place": "Dziedziniec"},
  {"day": "czwartek", "hour": "7:50", "teacher": ["Sala"], "place": "Budynek A"},
  {"day": "czwartek", "hour": "8:45", "teacher": ["Trela"], "place": "Budynek A"},
  {"day": "czwartek", "hour": "9:40", "teacher": ["Trela"], "place": "Budynek A"},
  {"day": "czwartek", "hour": "10:35", "teacher": ["Trela"], "place": "Budynek A"},
  {"day": "czwartek", "hour": "11:30", "teacher": ["Słomski"], "place": "Budynek A"},
  {"day": "czwartek", "hour": "12:25", "teacher": ["Słomski"], "place": "Budynek A"},
  {"day": "czwartek", "hour": "13:20", "teacher": ["Wrona"], "place": "Budynek A"},
  {"day": "czwartek", "hour": "14:20", "teacher": ["Rzemińska"], "place": "Budynek A"},
  {"day": "czwartek", "hour": "7:50", "teacher": ["Łukaszuk"], "place": "Budynek A 1piętro"},
  {"day": "czwartek", "hour": "8:45", "teacher": ["Wrotna"], "place": "Budynek A 1piętro"},
  {"day": "czwartek", "hour": "9:40", "teacher": ["Woźniak"], "place": "Budynek A 1piętro"},
  {"day": "czwartek", "hour": "10:35", "teacher": ["Wrona"], "place": "Budynek A 1piętro"},
  {"day": "czwartek", "hour": "11:30", "teacher": ["Kajetanowicz"], "place": "Budynek A 1piętro"},
  {"day": "czwartek", "hour": "12:25", "teacher": ["Witkowski"], "place": "Budynek A 1piętro"},
  {"day": "czwartek", "hour": "7:50", "teacher": ["Boruk", "Kajetanowicz"], "place": "Boisko"},
  {"day": "czwartek", "hour": "8:45", "teacher": ["Sala", "Kajetanowicz"], "place": "Boisko"},
  {"day": "czwartek", "hour": "9:40", "teacher": ["Sala", "Dyła"], "place": "Boisko"},
  {"day": "czwartek", "hour": "10:35", "teacher": ["Kupczyk", "Nogawka"], "place": "Boisko"},
  {"day": "czwartek", "hour": "11:30", "teacher": ["Szkudlarek", "Szik S."], "place": "Boisko"},
  {"day": "czwartek", "hour": "12:25", "teacher": ["Jop", "Rzemińska"], "place": "Boisko"},
  {"day": "czwartek", "hour": "13:20", "teacher": ["Witkowski", "Foryt"], "place": "Boisko"},
  {"day": "czwartek", "hour": "14:20", "teacher": ["Długosz-Pasieka"], "place": "Boisko"},
  {"day": "czwartek", "hour": "7:50", "teacher": ["Skórzecka"], "place": "Budynek B parter + WC"},
  {"day": "czwartek", "hour": "8:45", "teacher": ["Długosz-Pasieka"], "place": "Budynek B parter + WC"},
  {"day": "czwartek", "hour": "9:40", "teacher": ["Długosz-Pasieka"], "place": "Budynek B parter + WC"},
  {"day": "czwartek", "hour": "10:35", "teacher": ["Wadowski"], "place": "Budynek B parter + WC"},
  {"day": "czwartek", "hour": "11:30", "teacher": ["Wadowski"], "place": "Budynek B parter + WC"},
  {"day": "czwartek", "hour": "12:25", "teacher": ["Szik S."], "place": "Budynek B parter + WC"},
  {"day": "czwartek", "hour": "13:20", "teacher": ["Rzemińska"], "place": "Budynek B parter + WC"},
  {"day": "czwartek", "hour": "7:50", "teacher": ["Wadowski"], "place": "Budynek B 1piętro"},
  {"day": "czwartek", "hour": "8:45", "teacher": ["Rzemińska"], "place": "Budynek B 1piętro"},
  {"day": "czwartek", "hour": "9:40", "teacher": ["Wrotna"], "place": "Budynek B 1piętro"},
  {"day": "czwartek", "hour": "10:35", "teacher": ["Witkowski"], "place": "Budynek B 1piętro"},
  {"day": "czwartek", "hour": "11:30", "teacher": ["Nogawka"], "place": "Budynek B 1piętro"},
  {"day": "czwartek", "hour": "12:25", "teacher": ["Woźniak"], "place": "Budynek B 1piętro"},
  {"day": "czwartek", "hour": "13:20", "teacher": ["Rzemińska"], "place": "Budynek B 1piętro"},
  {"day": "piątek", "hour": "7:50", "teacher": ["Szik S."], "place": "Front"},
  {"day": "piątek", "hour": "8:45", "teacher": ["Nogawka"], "place": "Front"},
  {"day": "piątek", "hour": "9:40", "teacher": ["Nogawka"], "place": "Front"},
  {"day": "piątek", "hour": "7:50", "teacher": ["Wysocka"], "place": "Dziedziniec"},
  {"day": "piątek", "hour": "8:45", "teacher": ["Sala"], "place": "Dziedziniec"},
  {"day": "piątek", "hour": "9:40", "teacher": ["Trela"], "place": "Dziedziniec"},
  {"day": "piątek", "hour": "10:35", "teacher": ["Trela"], "place": "Dziedziniec"},
  {"day": "piątek", "hour": "11:30", "teacher": ["Słomski"], "place": "Dziedziniec"},
  {"day": "piątek", "hour": "12:25", "teacher": ["Wrona"], "place": "Dziedziniec"},
  {"day": "piątek", "hour": "13:20", "teacher": ["Długosz-Pasieka"], "place": "Dziedziniec"},
  {"day": "piątek", "hour": "14:20", "teacher": ["Wrotna"], "place": "Dziedziniec"},
  {"day": "piątek", "hour": "7:50", "teacher": ["Wadowski"], "place": "Budynek A"},
  {"day": "piątek", "hour": "8:45", "teacher": ["Wysocka"], "place": "Budynek A"},
  {"day": "piątek", "hour": "9:40", "teacher": ["Woźniak"], "place": "Budynek A"},
  {"day": "piątek", "hour": "10:35", "teacher": ["Witkowski"], "place": "Budynek A"},
  {"day": "piątek", "hour": "11:30", "teacher": ["Długosz-Pasieka"], "place": "Budynek A"},
  {"day": "piątek", "hour": "12:25", "teacher": ["Długosz-Pasieka"], "place": "Budynek A"},
  {"day": "piątek", "hour": "7:50", "teacher": null, "place": "Budynek A 1piętro"},
  {"day": "piątek", "hour": "8:45", "teacher": ["Rzemińska"], "place": "Budynek A 1piętro"},
  {"day": "piątek", "hour": "9:40", "teacher": ["Wysocka"], "place": "Budynek A 1piętro"},
  {"day": "piątek", "hour": "10:35", "teacher": ["Jop"], "place": "Budynek A 1piętro"},
  {"day": "piątek", "hour": "11:30", "teacher": ["Sala"], "place": "Budynek A 1piętro"},
  {"day": "piątek", "hour": "7:50", "teacher": ["Foryt", "Sala"], "place": "Boisko"},
  {"day": "piątek", "hour": "8:45", "teacher": ["Woźniak", "Kajetanowicz"], "place": "Boisko"},
  {"day": "piątek", "hour": "9:40", "teacher": ["Dyła", "Szik S."], "place": "Boisko"},
  {"day": "piątek", "hour": "10:35", "teacher": ["Szik S.", "Dyła"], "place": "Boisko"},
  {"day": "piątek", "hour": "11:30", "teacher": ["Trela", "Wrotna"], "place": "Boisko"},
  {"day": "piątek", "hour": "12:25", "teacher": ["Trela", "Kajetanowicz"], "place": "Boisko"},
  {"day": "piątek", "hour": "13:20", "teacher": ["Wrotna"], "place": "Boisko"},
  {"day": "piątek", "hour": "7:50", "teacher": ["Szkudlarek"], "place": "Budynek B parter + WC"},
  {"day": "piątek", "hour": "8:45", "teacher": ["Szkudlarek"], "place": "Budynek B parter + WC"},
  {"day": "piątek", "hour": "9:40", "teacher": ["Rzemińska"], "place": "Budynek B parter + WC"},
  {"day": "piątek", "hour": "10:35", "teacher": ["Rzemińska"], "place": "Budynek B parter + WC"},
  {"day": "piątek", "hour": "11:30", "teacher": ["Jop"], "place": "Budynek B parter + WC"},
  {"day": "piątek", "hour": "12:25", "teacher": ["Wrotna"], "place": "Budynek B parter + WC"},
  {"day": "piątek", "hour": "13:20", "teacher": ["Wadowski"], "place": "Budynek B parter + WC"},
  {"day": "piątek", "hour": "7:50", "teacher": ["Trela"], "place": "Budynek B 1piętro"},
  {"day": "piątek", "hour": "8:45", "teacher": ["Kupczyk"], "place": "Budynek B 1piętro"},
  {"day": "piątek", "hour": "9:40", "teacher": ["Kupczyk"], "place": "Budynek B 1piętro"},
  {"day": "piątek", "hour": "10:35", "teacher": ["Sala"], "place": "Budynek B 1piętro"},
  {"day": "piątek", "hour": "11:30", "teacher": ["Wadowski"], "place": "Budynek B 1piętro"},
  {"day": "piątek", "hour": "12:25", "teacher": ["Jop"], "place": "Budynek B 1piętro"},
  {"day": "piątek", "hour": "13:20", "teacher": ["Wadowski"], "place": "Budynek B 1piętro"}
]